odoo8_addon_project_categ_issue-8.0.0.1.0.99.dev14-py2.7-nspkg.pth
odoo8_addon_project_categ_issue-8.0.0.1.0.99.dev14.dist-info/METADATA
odoo8_addon_project_categ_issue-8.0.0.1.0.99.dev14.dist-info/RECORD
odoo8_addon_project_categ_issue-8.0.0.1.0.99.dev14.dist-info/WHEEL
odoo8_addon_project_categ_issue-8.0.0.1.0.99.dev14.dist-info/namespace_packages.txt
odoo8_addon_project_categ_issue-8.0.0.1.0.99.dev14.dist-info/top_level.txt
odoo_addons/project_categ_issue/__init__.py
odoo_addons/project_categ_issue/__openerp__.py
odoo_addons/project_categ_issue/project_categ_model.py
odoo_addons/project_categ_issue/project_categ_view.xml
odoo_addons/project_categ_issue/i18n/de.po
odoo_addons/project_categ_issue/i18n/es.po
odoo_addons/project_categ_issue/i18n/es_MX.po
odoo_addons/project_categ_issue/i18n/fi.po
odoo_addons/project_categ_issue/i18n/fr.po
odoo_addons/project_categ_issue/i18n/hr.po
odoo_addons/project_categ_issue/i18n/project_categ_issue.pot
odoo_addons/project_categ_issue/i18n/pt.po
odoo_addons/project_categ_issue/i18n/pt_BR.po
odoo_addons/project_categ_issue/i18n/pt_PT.po
odoo_addons/project_categ_issue/i18n/sl.po
odoo_addons/project_categ_issue/i18n/zh_CN.po
odoo_addons/project_categ_issue/static/description/icon.png
